rzbd2i/__init__.py
rzbd2i/glavni.py
rzbd2i/mymodule/__init__.py
rzbd2i/mymodule/myfunctions.py
rzbd2i-0.0.1.dist-info/METADATA
rzbd2i-0.0.1.dist-info/RECORD
rzbd2i-0.0.1.dist-info/WHEEL
rzbd2i-0.0.1.dist-info/top_level.txt
