Metadata-Version: 2.1
Name: rzbd2i
Version: 0.0.1
Summary: Exemple pour pip install
Home-page: UNKNOWN
Author: Example Author
Author-email: marrkonni@yahoo.com
License: UNKNOWN
Platform: UNKNOWN
Classifier: Programming Language :: Python :: 3
Classifier: License :: OSI Approved :: MIT License
Classifier: Operating System :: OS Independent
